hass_inspirair/__init__.py
hass_inspirair/__main__.py
hass_inspirair/config.py
hass_inspirair/env_config.py
hass_inspirair/ha/__init__.py
hass_inspirair/ha/devices.py
hass_inspirair/ha/model.py
hass_inspirair/i18n/__init__.py
hass_inspirair/i18n/de/LC_MESSAGES/hass_inspirair.mo
hass_inspirair/i18n/de/LC_MESSAGES/hass_inspirair.po
hass_inspirair/i18n/en/LC_MESSAGES/hass_inspirair.mo
hass_inspirair/i18n/en/LC_MESSAGES/hass_inspirair.po
hass_inspirair/i18n/hass_inspirair.pot
hass_inspirair/main.py
hass_inspirair/modbus/__init__.py
hass_inspirair/modbus/client.py
hass_inspirair/modbus/model.py
hass_inspirair/mqtt/__init__.py
hass_inspirair/mqtt/actions.py
hass_inspirair/mqtt/client.py
hass_inspirair-0.6.0.dist-info/LICENSE
hass_inspirair-0.6.0.dist-info/METADATA
hass_inspirair-0.6.0.dist-info/WHEEL
hass_inspirair-0.6.0.dist-info/entry_points.txt
hass_inspirair-0.6.0.dist-info/RECORD
