Metadata-Version: 2.1
Name: hass_inspirair
Version: 0.6.0
Summary: 
Home-page: https://the-smartest-home.github.io/hass_inspirair/
License: OSI Approved :: Apache Software License
Author: Kraus, Vadim
Author-email: 38394456+VadimKraus@users.noreply.github.com
Requires-Python: >=3.9,<3.14
Classifier: Development Status :: 4 - Beta
Classifier: License :: Other/Proprietary License
Classifier: Programming Language :: Python :: 3
Classifier: Programming Language :: Python :: 3.9
Classifier: Programming Language :: Python :: 3.10
Classifier: Programming Language :: Python :: 3.11
Classifier: Programming Language :: Python :: 3.12
Classifier: Programming Language :: Python :: 3.13
Requires-Dist: aiomqtt (>=2.0.0,<3.0.0)
Requires-Dist: pydantic (>=2.9.2,<3.0.0)
Requires-Dist: pymodbus[serial] (>=3.7.4,<4.0.0)
Project-URL: Documentation, https://the-smartest-home.github.io/hass_inspirair/
Project-URL: Repository, https://github.com/The-Smartest-Home/hass_inspirair
